d_treevis/__init__.py
d_treevis/decision_tree_vis.py
d_treevis-1.0.0.dist-info/LICENSE
d_treevis-1.0.0.dist-info/METADATA
d_treevis-1.0.0.dist-info/WHEEL
d_treevis-1.0.0.dist-info/top_level.txt
d_treevis-1.0.0.dist-info/RECORD
